{
  "version": 1,
  "generated_at": "2026-04-13 21:31:04 北京时间",
  "platform_labels": {
    "x-cdp": "X.com(CDP)"
  },
  "posts": {
    "x-cdp": {
      "https://x.com/cj3214567667/status/2043607629663256978": {
        "href": "https://x.com/cj3214567667/status/2043607629663256978",
        "published_at": "",
        "published_iso": "",
        "time_label": "",
        "is_pinned": false,
        "title": "普通人零基础玩转AI音乐创作，月入过万保姆级教程！（2026最新版）",
        "raw": "普通人零基础玩转AI音乐创作，月入过万保姆级教程！（2026最新版）",
        "author": "@cj3214567667",
        "rank": 1,
        "category": "following"
      },
      "https://x.com/Jucom_ZH/status/2043571611266420921": {
        "href": "https://x.com/Jucom_ZH/status/2043571611266420921",
        "published_at": "",
        "published_iso": "",
        "time_label": "",
        "is_pinned": false,
        "title": "最后一条评论可以获得这套",
        "raw": "最后一条评论可以获得这套",
        "author": "@Jucom_ZH",
        "rank": 2,
        "category": "following"
      },
      "https://x.com/qg7777/status/2043538692481102223": {
        "href": "https://x.com/qg7777/status/2043538692481102223",
        "published_at": "",
        "published_iso": "",
        "time_label": "",
        "is_pinned": false,
        "title": "只要Money给到位！ 美人鱼也可以……",
        "raw": "只要Money给到位！\n美人鱼也可以……",
        "author": "@qg7777",
        "rank": 3,
        "category": "following"
      },
      "https://x.com/laowu3677/status/2043631554128445767": {
        "href": "https://x.com/laowu3677/status/2043631554128445767",
        "published_at": "",
        "published_iso": "",
        "time_label": "",
        "is_pinned": false,
        "title": "刚入圈的时候，总希望能有个地方，大家一起交流、一起学习、一起成长 后来发现合适的圈子太少，于是我自己建了个小社群，只做纯粹的信息分享和经验交流 之前老社群因为微信被封，停了好久 现在统一说一声：我重新建群了 想一起聊的朋友可以一键三连加我微信",
        "raw": "刚入圈的时候，总希望能有个地方，大家一起交流、一起学习、一起成长\n\n后来发现合适的圈子太少，于是我自己建了个小社群，只做纯粹的信息分享和经验交流\n\n之前老社群因为微信被封，停了好久\n现在统一说一声：我重新建群了\n\n想一起聊的朋友可以一键三连加我微信",
        "author": "@laowu3677",
        "rank": 4,
        "category": "following"
      },
      "https://x.com/VincentLogic/status/2043352690428711223": {
        "href": "https://x.com/VincentLogic/status/2043352690428711223",
        "published_at": "",
        "published_iso": "",
        "time_label": "",
        "is_pinned": false,
        "title": "大学生凌晨3点创业有多拼？看完不敢躺平了！太卷了！",
        "raw": "大学生凌晨3点创业有多拼？看完不敢躺平了！太卷了！",
        "author": "@VincentLogic",
        "rank": 5,
        "category": "following"
      },
      "https://x.com/phill76815/status/2043538913583923298": {
        "href": "https://x.com/phill76815/status/2043538913583923298",
        "published_at": "",
        "published_iso": "",
        "time_label": "",
        "is_pinned": false,
        "title": "美女原味儿的bra，不要998，不要588，自取！哈哈！ 这个海外小姐姐太会玩了，哈哈！ 飞机上玩魔术脱bra！ 看到最后有彩蛋！！ ，特朗普对封锁霍尔木兹海峡围而不打真正的目的是什么？何意味？ 我以前一直认为美国需要武力登陆，控制霍尔木兹海峡，才符合最大的利益，但从目前美伊首轮谈判失败，特朗普采取外围封锁霍尔木兹海峡，突然发现他真实的目的，细思极恐！",
        "raw": "美女原味儿的bra，不要998，不要588，自取！哈哈！\n\n这个海外小姐姐太会玩了，哈哈！\n\n飞机上玩魔术脱bra！\n\n看到最后有彩蛋！！ ，特朗普对封锁霍尔木兹海峡围而不打真正的目的是什么？何意味？\n\n我以前一直认为美国需要武力登陆，控制霍尔木兹海峡，才符合最大的利益，但从目前美伊首轮谈判失败，特朗普采取外围封锁霍尔木兹海峡，突然发现他真实的目的，细思极恐！",
        "author": "@phill76815",
        "rank": 6,
        "category": "following"
      },
      "https://x.com/elonmusk/status/2043420251661197405": {
        "href": "https://x.com/elonmusk/status/2043420251661197405",
        "published_at": "",
        "published_iso": "",
        "time_label": "",
        "is_pinned": false,
        "title": "South Africa is doing Apartheid 2.0 We will put an end to Apartheid 2.0, we will end anti-White racism x.com/elonmusk/statu…",
        "raw": "South Africa is doing Apartheid 2.0 We will put an end to Apartheid 2.0, we will end anti-White racism x.com/elonmusk/statu…",
        "author": "@elonmusk",
        "rank": 7,
        "category": "following"
      },
      "https://x.com/xiaoyubtc/status/2043598209801691259": {
        "href": "https://x.com/xiaoyubtc/status/2043598209801691259",
        "published_at": "",
        "published_iso": "",
        "time_label": "",
        "is_pinned": false,
        "title": "工欲善其事，必先利其器。 汇总了一下币圈常用的数据/投研工具。 感觉 X 上有价值的信息越来越少，噪音很大。 只靠刷推，很难建立真正稳定的信息优势。 所以，多扩展信息来源，学会借助工具看数据、做验证、找增量信息。 下一步，我打算研究如何把这些工具和 OpenClaw 低成本打通。 //",
        "raw": "工欲善其事，必先利其器。\n汇总了一下币圈常用的数据/投研工具。\n\n感觉 X 上有价值的信息越来越少，噪音很大。\n只靠刷推，很难建立真正稳定的信息优势。\n\n所以，多扩展信息来源，学会借助工具看数据、做验证、找增量信息。\n\n下一步，我打算研究如何把这些工具和 OpenClaw 低成本打通。\n\n//",
        "author": "@xiaoyubtc",
        "rank": 8,
        "category": "following"
      },
      "https://x.com/CryptoSol33/status/2043553243318374412": {
        "href": "https://x.com/CryptoSol33/status/2043553243318374412",
        "published_at": "",
        "published_iso": "",
        "time_label": "",
        "is_pinned": false,
        "title": "全网最全 Polymarket 新手入门指南来啦 Polymarket新手看这篇就够了，零基础也能上手 这篇没有废话，注册、充值、下单、提现，一步一图，手把手带你走一遍。",
        "raw": "全网最全 Polymarket 新手入门指南来啦\n\nPolymarket新手看这篇就够了，零基础也能上手\n\n这篇没有废话，注册、充值、下单、提现，一步一图，手把手带你走一遍。",
        "author": "@CryptoSol33",
        "rank": 9,
        "category": "for_you_topup"
      }
    }
  }
}